blocks_and_pipes/__init__.py
blocks_and_pipes/blocks.py
blocks_and_pipes/pipes.py
blocks_and_pipes-0.0.2.dist-info/METADATA
blocks_and_pipes-0.0.2.dist-info/WHEEL
blocks_and_pipes-0.0.2.dist-info/licenses/LICENSE
blocks_and_pipes-0.0.2.dist-info/RECORD
