Metadata-Version: 2.3
Name: blocks_and_pipes
Version: 0.0.2
Summary: Blocks and Pipes for Python
Project-URL: Homepage, https://github.com/bschnitz/blocks_and_pipes
Project-URL: Issues, https://github.com/bschnitz/blocks_and_pipes/issues
Author-email: Benjamin Schnitzler <regenbogenbauer@web.de>
License-File: LICENSE
Classifier: License :: OSI Approved :: MIT License
Classifier: Operating System :: OS Independent
Classifier: Programming Language :: Python :: 3
Requires-Python: >=3.11
